main.py
setup.py
ddim.egg-info/PKG-INFO
ddim.egg-info/SOURCES.txt
ddim.egg-info/dependency_links.txt
ddim.egg-info/requires.txt
ddim.egg-info/top_level.txt